sentm/__init__.py
sentm/complexitext.py
sentm/data/lemma-30k-2017.txt
sentm/data/lemma_dict_raw.json
sentm/data/lemma_dict_scaled.json
sentm/sentm.py
sentm-0.2.1.dist-info/METADATA
sentm-0.2.1.dist-info/WHEEL
sentm-0.2.1.dist-info/RECORD
