Metadata-Version: 2.1
Name: sentm
Version: 0.2.1
Summary: Lexical Sentiment and Text Complexity Analysis in Danish
Home-page: https://github.com/MadsLang/senTM
Author: MadsLang
Author-email: madslangs@gmail.com
Requires-Python: >=3.9,<4.0
Classifier: Programming Language :: Python :: 3
Classifier: Programming Language :: Python :: 3.9
Classifier: Programming Language :: Python :: 3.10
Classifier: Programming Language :: Python :: 3.11
Requires-Dist: ipykernel (>=6.22.0,<7.0.0)
Requires-Dist: lemmy (>=2.1.0,<3.0.0)
Requires-Dist: pandas (>=1.5.2,<2.0.0)
Requires-Dist: spacy (>=3.5.0,<4.0.0)
Project-URL: Repository, https://github.com/MadsLang/senTM
